{
	"name": "Trophy",
	"plugin-id": "Sprite",
	"sid": 867537811011787,
	"isGlobal": false,
	"editorNewInstanceIsReplica": true,
	"instanceVariables": [],
	"behaviorTypes": [],
	"effectTypes": [],
	"animations": {
		"items": [
			{
				"frames": [
					{
						"width": 673,
						"height": 672,
						"originX": 0.5,
						"originY": 0.5,
						"originalSource": "",
						"exportFormat": "lossless",
						"exportQuality": 0.8,
						"fileType": "image/png",
						"imageSpriteId": 515763,
						"collisionPoly": {
							"points": [
								0.4487369985141159,
								0.08333333333333333,
								0.7815750371471025,
								0.14136904761904762,
								0.8439821693907875,
								0.28869047619047616,
								0.8439821693907875,
								0.3854166666666667,
								0.7592867756315007,
								0.9479166666666666,
								0.2213967310549777,
								0.9241071428571429,
								0.16047548291233285,
								0.3869047619047619,
								0.1649331352154532,
								0.26339285714285715,
								0.24814264487369986,
								0.11607142857142858
							]
						},
						"useCollisionPoly": true,
						"duration": 1,
						"tag": ""
					}
				],
				"sid": 563923562425276,
				"name": "Animation 1",
				"isLooping": false,
				"isPingPong": false,
				"repeatCount": 1,
				"repeatTo": 0,
				"speed": 5
			}
		],
		"subfolders": []
	}
}